GaussBin_distribution/__init__.py
GaussBin_distribution/binomial.py
GaussBin_distribution/gaussian.py
GaussBin_distribution/generalDistribution.py
GaussBin_distribution-1.2.dist-info/METADATA
GaussBin_distribution-1.2.dist-info/WHEEL
GaussBin_distribution-1.2.dist-info/top_level.txt
GaussBin_distribution-1.2.dist-info/RECORD
