Metadata-Version: 2.1
Name: GaussBin-distribution
Version: 1.2
Summary: Gaussian Distributions & Binomial Distributions
Home-page: UNKNOWN
Author: Faisal Lawan
Author-email: faisallawan08@gmail.com
License: UNKNOWN
Platform: UNKNOWN
